transimage-1.0.0.dist-info/METADATA
transimage-1.0.0.dist-info/WHEEL
transimage-1.0.0.dist-info/entry_points.txt
transimage-1.0.0.dist-info/licenses/LICENSE
transimage/__init__.py
transimage/__main__.py
transimage/image_collector.py
transimage/image_converter.py
transimage-1.0.0.dist-info/RECORD
