Metadata-Version: 2.1
Name: transimage
Version: 1.0.0
Summary: Converts images from one format to another using Pillow. Supports JPG, PNG, BMP, and WebP.
Author-Email: Daethyra <109057945+Daethyra@users.noreply.github.com>
License: MIT
Requires-Python: <4.0,>=3.13
Requires-Dist: pillow<12.0.0,>=11.0.0
